netplanner/__init__.py
netplanner/__main__.py
netplanner/config.py
netplanner/interfaces/__init__.py
netplanner/interfaces/base.py
netplanner/interfaces/l2/__init__.py
netplanner/interfaces/l2/bond.py
netplanner/interfaces/l2/bridge.py
netplanner/interfaces/l2/dummy.py
netplanner/interfaces/l2/ethernet.py
netplanner/interfaces/l2/veth.py
netplanner/interfaces/l2/vlan.py
netplanner/interfaces/l2/vrf.py
netplanner/interfaces/l2/vxlan.py
netplanner/interfaces/l3/__init__.py
netplanner/interfaces/l3/nameserver.py
netplanner/interfaces/l3/route.py
netplanner/interfaces/l3/routing_policy.py
netplanner/interfaces/match_object.py
netplanner/interfaces/typing.py
netplanner/loader/__init__.py
netplanner/loader/config.py
netplanner/loader/templates.py
netplanner/loader/util.py
netplanner/providers/__init__.py
netplanner/providers/networkd/__init__.py
netplanner/providers/networkd/files/10-vxlan-default.link
netplanner/providers/networkd/files/__init__.py
netplanner/providers/networkd/provider.py
netplanner/providers/networkd/templates/__init__.py
netplanner/providers/networkd/templates/additionals.j2
netplanner/providers/networkd/templates/netdev_includes/__init__.py
netplanner/providers/networkd/templates/netdev_includes/bond.j2
netplanner/providers/networkd/templates/netdev_includes/bridge.j2
netplanner/providers/networkd/templates/netdev_includes/veth.j2
netplanner/providers/networkd/templates/netdev_includes/vlan.j2
netplanner/providers/networkd/templates/netdev_includes/vrf.j2
netplanner/providers/networkd/templates/netdev_includes/vxlan.j2
netplanner/providers/networkd/templates/network_includes/__init__.py
netplanner/providers/networkd/templates/network_includes/bridge_port.j2
netplanner/providers/networkd/templates/network_includes/link.j2
netplanner/providers/networkd/templates/network_includes/match.j2
netplanner/providers/networkd/templates/network_includes/nameserver.j2
netplanner/providers/networkd/templates/network_includes/network.j2
netplanner-0.14.10.dist-info/LICENSE
netplanner-0.14.10.dist-info/METADATA
netplanner-0.14.10.dist-info/NOTICE
netplanner-0.14.10.dist-info/WHEEL
netplanner-0.14.10.dist-info/entry_points.txt
netplanner-0.14.10.dist-info/RECORD
