Metadata-Version: 2.1
Name: netplanner
Version: 0.14.10
Summary: Mimir the Netplanner is the ground of all network wisdöm
License: GPL-3.0-only
Author: Marcel Fest
Author-email: marcel.fest@telekom.de
Requires-Python: >=3.10,<4
Classifier: License :: OSI Approved :: GNU General Public License v3 (GPLv3)
Classifier: Programming Language :: Python :: 3
Classifier: Programming Language :: Python :: 3.10
Classifier: Programming Language :: Python :: 3.11
Classifier: Programming Language :: Python :: 3.12
Requires-Dist: Jinja2 (>=3.1.1,<4.0.0)
Requires-Dist: PyYAML (>=6.0,<7.0)
Requires-Dist: dacite (>=1.8.1,<2.0.0)
Requires-Dist: fqdn (>=1.5.1,<2.0.0)
